{
  "routes": [
    {
      "method": "GET",
      "path": "/section-disclaimer",
      "handler": "section-disclaimer.find",
      "config": {
        "policies": []
      }
    },
    {
      "method": "PUT",
      "path": "/section-disclaimer",
      "handler": "section-disclaimer.update",
      "config": {
        "policies": []
      }
    },
    {
      "method": "DELETE",
      "path": "/section-disclaimer",
      "handler": "section-disclaimer.delete",
      "config": {
        "policies": []
      }
    }
  ]
}
