{
  "collectionName": "components_page_content_services",
  "info": {
    "name": "Service",
    "icon": "check",
    "description": ""
  },
  "options": {},
  "attributes": {
    "title": {
      "type": "string",
      "required": true
    },
    "link": {
      "type": "string",
      "required": true
    },
    "image": {
      "model": "file",
      "via": "related",
      "allowedTypes": [
        "files",
        "images",
        "videos"
      ],
      "plugin": "upload",
      "required": true
    },
    "examples": {
      "type": "component",
      "repeatable": true,
      "component": "page-content.service-example",
      "required": true
    }
  }
}
